funqtor/__init__.py
funqtor/__main__.py
funqtor/building/__init__.py
funqtor/building/build_tools.py
funqtor/building/compiling.py
funqtor/building/runner.py
funqtor/helpers.py
funqtor/initializing.py
funqtor/managing/__init__.py
funqtor/managing/filegenerator.py
funqtor/managing/installing.py
funqtor/packaging/__init__.py
funqtor/packaging/packager.py
funqtor/packaging/publisher.py
funqtor-0.1.3.dist-info/entry_points.txt
funqtor-0.1.3.dist-info/METADATA
funqtor-0.1.3.dist-info/WHEEL
funqtor-0.1.3.dist-info/RECORD
